tirem/__init__.py
tirem/tirem3.cp38-win_amd64.pyd
tirem-3.0.1.dist-info/LICENSE
tirem-3.0.1.dist-info/METADATA
tirem-3.0.1.dist-info/WHEEL
tirem-3.0.1.dist-info/top_level.txt
tirem-3.0.1.dist-info/RECORD
