Metadata-Version: 2.1
Name: tirem
Version: 3.0.1
Summary: TIREM Python API
Home-page: https://github.com/talos-gis/rfmodel
Author: Idan Miara
Author-email: idan@miara.com
License: MIT
Platform: UNKNOWN
Requires-Dist: tirem-bin
